zowe_apiml_onboarding_enabler_python/__init__.py
zowe_apiml_onboarding_enabler_python/config.py
zowe_apiml_onboarding_enabler_python/custom_http_client.py
zowe_apiml_onboarding_enabler_python/registration.py
zowe_apiml_onboarding_enabler_python-3.2.3.dist-info/METADATA
zowe_apiml_onboarding_enabler_python-3.2.3.dist-info/WHEEL
zowe_apiml_onboarding_enabler_python-3.2.3.dist-info/top_level.txt
zowe_apiml_onboarding_enabler_python-3.2.3.dist-info/RECORD
