Metadata-Version: 2.4
Name: zowe-apiml-onboarding-enabler-python
Version: 3.2.3
Summary: Python enabler for Zowe API Mediation Layer
Author: Zowe Project
License: EPL-2.0
Requires-Python: >=3.10
Requires-Dist: requests
Requires-Dist: pyyaml
